{"name":"Belial, the Crimson Lord","attribute":"<img src=\"_images/icons/1x1.gif\" class=\"fdb-icon-r\">&nbsp;Fire","type":"Resonator","cmc":0,"racesOrTraits":["Demon"],"text":"Continuous: Your resonators gain Explode.\nContinuous: When your resonator put into a graveyard by Explode, you may discard a card from your hand. If you do, return that resonator to its owner's hand.","set":"The Dawn of Valhalla","code":"1-074 R","rarity":"R","thumbnailImage":"app/assets/img/cards/1/074.jpg","cardImage":"http://db.fowtcg.us/cards/1/074.jpg"}