{"name":"Bursting Shot","attribute":"<img src=\"_images/icons/1x1.gif\" class=\"fdb-icon-r\">&nbsp;Fire","type":"Spell:Chant-Instant","cmc":0,"racesOrTraits":[],"text":"Break: This card deals [the number of cards in your magic stone area x 100] damage to target resonator.\nBanish a recovered card in your magic stone area. This card deals 600 damage to target resonator or player.","set":"The Dawn of Valhalla","code":"1-088 C","rarity":"C","thumbnailImage":"app/assets/img/cards/1/088.jpg","cardImage":"http://db.fowtcg.us/cards/1/088.jpg"}