{"name":"Magic Tricker","attribute":"<img src=\"_images/icons/1x1.gif\" class=\"fdb-icon-u\">&nbsp;Water","type":"Resonator","cmc":0,"racesOrTraits":["Clown"],"text":"Break: Put this card into your hand.\nEnter: Put all cards in your hand to your main deck, shuffle it and draw cards equal to the number of cards you had from your main deck.","set":"The Dawn of Valhalla","code":"1-112 C","rarity":"C","thumbnailImage":"app/assets/img/cards/1/112.jpg","cardImage":"http://db.fowtcg.us/cards/1/112.jpg"}