{"name":"Spiral Flair","attribute":"<img src=\"_images/icons/1x1.gif\" class=\"fdb-icon-r\">&nbsp;Fire","type":"Spell:Chant","cmc":0,"racesOrTraits":[],"text":"This card deals 600 damage to target resonator. If it deals more damage than DEF of the resonator, this card deals number of damage more than the DEF to the controller of that resonator.","set":"The Shaft of Light of Valhalla","code":"3-044 U","rarity":"U","thumbnailImage":"app/assets/img/cards/3/044.jpg","cardImage":"http://db.fowtcg.us/cards/3/044.jpg"}