{"name":"Caith Sith Roun, the Weaver of Miracles","attribute":"<img src=\"_images/icons/1x1.gif\" class=\"fdb-icon-g\">&nbsp;Wind","type":"Resonator","cmc":0,"racesOrTraits":["Lycanthrope"],"text":"Break: Put this card into your hand.\nContinuous: Other resonators in your field cannot be returned to their owner's hand by opponent's spells and abilities.","set":"The Shaft of Light of Valhalla","code":"3-082 C","rarity":"C","thumbnailImage":"app/assets/img/cards/3/082.jpg","cardImage":"http://db.fowtcg.us/cards/3/082.jpg"}