{"name":"Runic Commander Demon, Akiot","attribute":"<img src=\"_images/icons/1x1.gif\" class=\"fdb-icon-r\">&nbsp;Fire, \n         <img src=\"_images/icons/1x1.gif\" class=\"fdb-icon-u\">&nbsp;Water","type":"Resonator","cmc":0,"racesOrTraits":["Seven Luminaries Demon"],"text":"When this card enters your field ? Put a mana counter on your J/ruler.\n<div class=\"fdb-separator-v-05\">","set":"Legacy Lost","code":"LEL-084 SR","rarity":"SR","thumbnailImage":"app/assets/img/cards/LEL/084.jpg","cardImage":"http://db.fowtcg.us/cards/lel/084.jpg"}