{"name":"Guardian of the Forest","attribute":"<img src=\"_images/icons/1x1.gif\" class=\"fdb-icon-g\">&nbsp;Wind","type":"Resonator","cmc":0,"racesOrTraits":["Beast"],"text":"<img src=\"_images/icons/1x1.gif\" class=\"fdb-icon-g\" alt=\"g\">: This card gains [+200/+200] until end of turn. Play this ability only once per turn.","set":"The Seven Kings of the Lands","code":"SKL-056 C","rarity":"C","thumbnailImage":"app/assets/img/cards/SKL/056.jpg","cardImage":"http://db.fowtcg.us/cards/skl/056.jpg"}