{"name":"Oz, the Great Wizard","attribute":"<img src=\"_images/icons/1x1.gif\" class=\"fdb-icon-g\">&nbsp;Wind","type":"Resonator","cmc":0,"racesOrTraits":["Fairy Tale"],"text":"Enter: Search your main deck for a spell card with total cost 1, reveal it and put it into your hand. If its name is \"Oz's Magic\", you may play it without pay ing its cost instead of putting it into your hand. Then shuffle your main deck.","set":"The Castle of Heaven and the Two Towers","code":"TAT-065 U","rarity":"U","thumbnailImage":"app/assets/img/cards/TAT/065.jpg","cardImage":"http://db.fowtcg.us/cards/tat/065.jpg"}