{"name":"Interdimensional Vessel, Apollo","attribute":"<img src=\"_images/icons/1x1.gif\" class=\"fdb-icon-v\">&nbsp;Void","type":"Regalia","cmc":0,"racesOrTraits":[],"text":"Your J-ruler gains Flying.\n<img src=\"_images/icons/1x1.gif\" class=\"fdb-icon-rest\">: Produce <img src=\"_images/icons/1x1.gif\" class=\"fdb-icon-m\" alt=\"m\">. Spend this will only to pay Awakening costs or to play Judgment or God's Art abilities of J/rulers with \"Kaguya\" in their name.\n<img src=\"_images/icons/1x1.gif\" class=\"fdb-icon-rest\">, banish this card: Return target resonator you control to its owner's hand.","set":"The Moonlit Savior","code":"TMS-094 R","rarity":"R","thumbnailImage":"app/assets/img/cards/TMS/094.jpg","cardImage":"http://db.fowtcg.us/cards/tms/094.jpg"}