{"name":"Veteran Master","attribute":"<img src=\"_images/icons/1x1.gif\" class=\"fdb-icon-w\">&nbsp;Light","type":"Resonator","cmc":0,"racesOrTraits":["Knight"],"text":"<img src=\"_images/icons/1x1.gif\" class=\"fdb-icon-rest\">: Target resonator with total cost of 2 or less gains [+200/+200] until end of turn.","set":"Faria, the Sacred Queen/Melgis, the Flame King","code":"VS01-015 C","rarity":"C","thumbnailImage":"app/assets/img/cards/VS01/015.jpg","cardImage":"http://db.fowtcg.us/cards/vs01/015.jpg"}